LICENSE
MANIFEST.in
README.md
setup.py
geneimpacts/__init__.py
geneimpacts/effect.py
geneimpacts.egg-info/PKG-INFO
geneimpacts.egg-info/SOURCES.txt
geneimpacts.egg-info/dependency_links.txt
geneimpacts.egg-info/not-zip-safe
geneimpacts.egg-info/top_level.txt
geneimpacts/tests/__init__.py
geneimpacts/tests/__init__.pyc
geneimpacts/tests/bcfts.txt.gz
geneimpacts/tests/snpeff-anns.txt.gz
geneimpacts/tests/test_impacts.py
geneimpacts/tests/test_impacts.pyc
geneimpacts/tests/vep-csqs.txt.gz