Metadata-Version: 1.1
Name: geneimpacts
Version: 0.3.5
Summary: normalize effects from variant annotation tools (snpEff, VEP)
Home-page: UNKNOWN
Author: Brent Pedersen
Author-email: bpederse@gmail.com
License: UNKNOWN
Platform: UNKNOWN
Classifier: Development Status :: 4 - Beta
Classifier: Intended Audience :: Science/Research
Classifier: License :: OSI Approved :: MIT License
Classifier: Topic :: Scientific/Engineering :: Bio-Informatics
